liveisstracker/__init__.py
liveisstracker/command_line.py
liveisstracker/track_iss.py
liveisstracker/PlotMap/MapBasePlot.py
liveisstracker/PlotMap/PlotlyFig.py
liveisstracker/PlotMap/__init__.py
liveisstracker/dbsql/__init__.py
liveisstracker/dbsql/dbconnections.py
liveisstracker/issTrack/__init__.py
liveisstracker/issTrack/issTracking.py
liveisstracker/issTrack/page_information.py
liveisstracker/mylogger/__init__.py
liveisstracker/mylogger/iss_logging.py
liveisstracker/tests/__init__.py
liveisstracker/tests/test_iss.py
liveisstracker-1.1.10.dist-info/METADATA
liveisstracker-1.1.10.dist-info/WHEEL
liveisstracker-1.1.10.dist-info/entry_points.txt
liveisstracker-1.1.10.dist-info/top_level.txt
liveisstracker-1.1.10.dist-info/RECORD
