Metadata-Version: 2.1
Name: liveisstracker
Version: 1.1.10
Summary: A CLI to get the current position, speed, passing country and image of the location of International Space Station on a map [#liveisstracker]. Source: LiveIssTracker Project from https://gitlab.com/manojm18/liveisstracker.
Home-page: https://github.com/manojmanivannan
Author: Manoj Manivannan
Author-email: manojm18@live.in
License: UNKNOWN
Platform: UNKNOWN
Requires-Dist: basemap
Requires-Dist: click
Requires-Dist: geographiclib
Requires-Dist: geopy
Requires-Dist: kaleido
Requires-Dist: matplotlib
Requires-Dist: pandas
Requires-Dist: plotly
Requires-Dist: six
Requires-Dist: tenacity
